src/Four Digit Seven Segment Driver/Counter Modulo/counter.vhd

library IEEE;
use IEEE.STD_LOGIC_1164.ALL;
use IEEE.NUMERIC_STD.ALL;

entity counter is
    Port (
		RST 	: in 	STD_LOGIC;
		CLK 	: in  STD_LOGIC;
      C_OUT : out STD_LOGIC_VECTOR (1 downto 0)
	);
end counter;

architecture Behavioral of counter is
	-- This signal will hold the current counter data.
	signal c_val: STD_LOGIC_VECTOR (1 downto 0);
	
begin
	
	process(CLK, RST)
	begin
	
	-- If reset occur, set counter to zero.
		if (RST = '1') then
			c_val <= (others => '0');
	-- If clock signal arrived, set counter to one upper value.
		elsif (CLK'event and CLK='1') then
			c_val <= STD_LOGIC_VECTOR(unsigned(c_val) + 1);
		end if;
		
	end process;
	
-- Export the data from c_val to c_out.
	C_OUT <= c_val;
	
end Behavioral;

src/Four Digit Seven Segment Driver/Counter Modulo/counterTest.vhdl
LIBRARY ieee;
USE ieee.std_logic_1164.ALL;
 
ENTITY counterTest IS
END counterTest;
 
ARCHITECTURE behavior OF counterTest IS 
 
    -- Component Declaration for the Unit Under Test (UUT)
 
    COMPONENT counter
    PORT(
         RST : IN  std_logic;
         CLK : IN  std_logic;
         C_OUT : OUT  std_logic_vector(1 downto 0)
        );
    END COMPONENT;
    

   --Inputs
   signal RST : std_logic := '0';
   signal CLK : std_logic := '0';

 	--Outputs
   signal C_OUT : std_logic_vector(1 downto 0);

   -- Clock period definitions
   constant CLK_period : time := 20 ns;
 
BEGIN
 
	-- Instantiate the Unit Under Test (UUT)
   uut: counter PORT MAP (RST => RST, CLK => CLK, C_OUT => C_OUT);

   -- Clock process definitions
   CLK_process :process
   begin
		CLK <= '0';
		wait for CLK_period/2;
		CLK <= '1';
		wait for CLK_period/2;
   end process;
 

   -- Stimulus process
   stim_proc: process
   begin		
      RST <= '1';
		wait for CLK_period;
		RST <= '0';
		wait;
   end process;
END;

src/Four Digit Seven Segment Driver/Counter Modulo/Simulation Files/sim.vcd
$date
  Sat Apr 23 21:31:50 2022
$end
$version
  GHDL v0
$end
$timescale
  1 fs
$end
$scope module standard $end
$upscope $end
$scope module textio $end
$upscope $end
$scope module std_logic_1164 $end
$upscope $end
$scope module numeric_std $end
$upscope $end
$scope module countertest $end
$var reg 1 ! rst $end
$var reg 1 " clk $end
$var reg 2 # c_out[1:0] $end
$scope module uut $end
$var reg 1 $ rst $end
$var reg 1 % clk $end
$var reg 2 & c_out[1:0] $end
$var reg 2 ' c_val[1:0] $end
$upscope $end
$upscope $end
$enddefinitions $end
#0
1!
0"
b00 #
1$
0%
b00 &
b00 '
#10000000
1"
1%
#20000000
0!
0"
0$
0%
#30000000
1"
b01 #
1%
b01 &
b01 '
#40000000
0"
0%
#50000000
1"
b10 #
1%
b10 &
b10 '
#60000000
0"
0%
#70000000
1"
b11 #
1%
b11 &
b11 '
#80000000
0"
0%
#90000000
1"
b00 #
1%
b00 &
b00 '
#100000000
0"
0%
#110000000
1"
b01 #
1%
b01 &
b01 '
#120000000
0"
0%
#130000000
1"
b10 #
1%
b10 &
b10 '
#140000000
0"
0%
#150000000
1"
b11 #
1%
b11 &
b11 '
#160000000
0"
0%
#170000000
1"
b00 #
1%
b00 &
b00 '
#180000000
0"
0%
#190000000
1"
b01 #
1%
b01 &
b01 '
#200000000
0"
0%
#210000000
1"
b10 #
1%
b10 &
b10 '
#220000000
0"
0%
#230000000
1"
b11 #
1%
b11 &
b11 '
#240000000
0"
0%
#250000000
1"
b00 #
1%
b00 &
b00 '
#260000000
0"
0%
#270000000
1"
b01 #
1%
b01 &
b01 '
#280000000
0"
0%
#290000000
1"
b10 #
1%
b10 &
b10 '
#300000000
0"
0%
#310000000
1"
b11 #
1%
b11 &
b11 '
#320000000
0"
0%
#330000000
1"
b00 #
1%
b00 &
b00 '
#340000000
0"
0%
#350000000
1"
b01 #
1%
b01 &
b01 '
#360000000
0"
0%
#370000000
1"
b10 #
1%
b10 &
b10 '
#380000000
0"
0%
#390000000
1"
b11 #
1%
b11 &
b11 '
#400000000
0"
0%
#410000000
1"
b00 #
1%
b00 &
b00 '
#420000000
0"
0%
#430000000
1"
b01 #
1%
b01 &
b01 '
#440000000
0"
0%
#450000000
1"
b10 #
1%
b10 &
b10 '
#460000000
0"
0%
#470000000
1"
b11 #
1%
b11 &
b11 '
#480000000
0"
0%
#490000000
1"
b00 #
1%
b00 &
b00 '
#500000000
0"
0%
#510000000
1"
b01 #
1%
b01 &
b01 '
#520000000
0"
0%
#530000000
1"
b10 #
1%
b10 &
b10 '
#540000000
0"
0%
#550000000
1"
b11 #
1%
b11 &
b11 '
#560000000
0"
0%
#570000000
1"
b00 #
1%
b00 &
b00 '
#580000000
0"
0%
#590000000
1"
b01 #
1%
b01 &
b01 '
#600000000
0"
0%
#610000000
1"
b10 #
1%
b10 &
b10 '
#620000000
0"
0%
#630000000
1"
b11 #
1%
b11 &
b11 '
#640000000
0"
0%
#650000000
1"
b00 #
1%
b00 &
b00 '
#660000000
0"
0%
#670000000
1"
b01 #
1%
b01 &
b01 '
#680000000
0"
0%
#690000000
1"
b10 #
1%
b10 &
b10 '
#700000000
0"
0%
#710000000
1"
b11 #
1%
b11 &
b11 '
#720000000
0"
0%
#730000000
1"
b00 #
1%
b00 &
b00 '
#740000000
0"
0%
#750000000
1"
b01 #
1%
b01 &
b01 '
#760000000
0"
0%
#770000000
1"
b10 #
1%
b10 &
b10 '
#780000000
0"
0%
#790000000
1"
b11 #
1%
b11 &
b11 '
#800000000
0"
0%
#810000000
1"
b00 #
1%
b00 &
b00 '
#820000000
0"
0%
#830000000
1"
b01 #
1%
b01 &
b01 '
#840000000
0"
0%
#850000000
1"
b10 #
1%
b10 &
b10 '
#860000000
0"
0%
#870000000
1"
b11 #
1%
b11 &
b11 '
#880000000
0"
0%
#890000000
1"
b00 #
1%
b00 &
b00 '
#900000000
0"
0%
#910000000
1"
b01 #
1%
b01 &
b01 '
#920000000
0"
0%
#930000000
1"
b10 #
1%
b10 &
b10 '
#940000000
0"
0%
#950000000
1"
b11 #
1%
b11 &
b11 '
#960000000
0"
0%
#970000000
1"
b00 #
1%
b00 &
b00 '
#980000000
0"
0%
#990000000
1"
b01 #
1%
b01 &
b01 '
#1000000000
0"
0%
#1010000000
1"
b10 #
1%
b10 &
b10 '
#1020000000
0"
0%
#1030000000
1"
b11 #
1%
b11 &
b11 '
#1040000000
0"
0%
#1050000000
1"
b00 #
1%
b00 &
b00 '
#1060000000
0"
0%
#1070000000
1"
b01 #
1%
b01 &
b01 '
#1080000000
0"
0%
#1090000000
1"
b10 #
1%
b10 &
b10 '
#1100000000
0"
0%
#1110000000
1"
b11 #
1%
b11 &
b11 '
#1120000000
0"
0%
#1130000000
1"
b00 #
1%
b00 &
b00 '
#1140000000
0"
0%
#1150000000
1"
b01 #
1%
b01 &
b01 '
#1160000000
0"
0%
#1170000000
1"
b10 #
1%
b10 &
b10 '
#1180000000
0"
0%
#1190000000
1"
b11 #
1%
b11 &
b11 '
#1200000000
0"
0%
#1210000000
1"
b00 #
1%
b00 &
b00 '
#1220000000
0"
0%
#1230000000
1"
b01 #
1%
b01 &
b01 '
#1240000000
0"
0%
#1250000000
1"
b10 #
1%
b10 &
b10 '
#1260000000
0"
0%
#1270000000
1"
b11 #
1%
b11 &
b11 '
#1280000000
0"
0%
#1290000000
1"
b00 #
1%
b00 &
b00 '
#1300000000
0"
0%
#1310000000
1"
b01 #
1%
b01 &
b01 '
#1320000000
0"
0%
#1330000000
1"
b10 #
1%
b10 &
b10 '
#1340000000
0"
0%
#1350000000
1"
b11 #
1%
b11 &
b11 '
#1360000000
0"
0%
#1370000000
1"
b00 #
1%
b00 &
b00 '
#1380000000
0"
0%
#1390000000
1"
b01 #
1%
b01 &
b01 '
#1400000000
0"
0%
#1410000000
1"
b10 #
1%
b10 &
b10 '
#1420000000
0"
0%
#1430000000
1"
b11 #
1%
b11 &
b11 '
#1440000000
0"
0%
#1450000000
1"
b00 #
1%
b00 &
b00 '
#1460000000
0"
0%
#1470000000
1"
b01 #
1%
b01 &
b01 '
#1480000000
0"
0%
#1490000000
1"
b10 #
1%
b10 &
b10 '
#1500000000
0"
0%
#1510000000
1"
b11 #
1%
b11 &
b11 '
#1520000000
0"
0%
#1530000000
1"
b00 #
1%
b00 &
b00 '
#1540000000
0"
0%
#1550000000
1"
b01 #
1%
b01 &
b01 '
#1560000000
0"
0%
#1570000000
1"
b10 #
1%
b10 &
b10 '
#1580000000
0"
0%
#1590000000
1"
b11 #
1%
b11 &
b11 '
#1600000000
0"
0%
#1610000000
1"
b00 #
1%
b00 &
b00 '
#1620000000
0"
0%
#1630000000
1"
b01 #
1%
b01 &
b01 '
#1640000000
0"
0%
#1650000000
1"
b10 #
1%
b10 &
b10 '
#1660000000
0"
0%
#1670000000
1"
b11 #
1%
b11 &
b11 '
#1680000000
0"
0%
#1690000000
1"
b00 #
1%
b00 &
b00 '
#1700000000
0"
0%
#1710000000
1"
b01 #
1%
b01 &
b01 '
#1720000000
0"
0%
#1730000000
1"
b10 #
1%
b10 &
b10 '
#1740000000
0"
0%
#1750000000
1"
b11 #
1%
b11 &
b11 '
#1760000000
0"
0%
#1770000000
1"
b00 #
1%
b00 &
b00 '
#1780000000
0"
0%
#1790000000
1"
b01 #
1%
b01 &
b01 '
#1800000000
0"
0%
#1810000000
1"
b10 #
1%
b10 &
b10 '
#1820000000
0"
0%
#1830000000
1"
b11 #
1%
b11 &
b11 '
#1840000000
0"
0%
#1850000000
1"
b00 #
1%
b00 &
b00 '
#1860000000
0"
0%
#1870000000
1"
b01 #
1%
b01 &
b01 '
#1880000000
0"
0%
#1890000000
1"
b10 #
1%
b10 &
b10 '
#1900000000
0"
0%
#1910000000
1"
b11 #
1%
b11 &
b11 '
#1920000000
0"
0%
#1930000000
1"
b00 #
1%
b00 &
b00 '
#1940000000
0"
0%
#1950000000
1"
b01 #
1%
b01 &
b01 '
#1960000000
0"
0%
#1970000000
1"
b10 #
1%
b10 &
b10 '
#1980000000
0"
0%
#1990000000
1"
b11 #
1%
b11 &
b11 '
#2000000000
0"
0%
#2010000000
1"
b00 #
1%
b00 &
b00 '
#2020000000
0"
0%
#2030000000
1"
b01 #
1%
b01 &
b01 '
#2040000000
0"
0%
#2050000000
1"
b10 #
1%
b10 &
b10 '
#2060000000
0"
0%
#2070000000
1"
b11 #
1%
b11 &
b11 '
#2080000000
0"
0%
#2090000000
1"
b00 #
1%
b00 &
b00 '
#2100000000
0"
0%
#2110000000
1"
b01 #
1%
b01 &
b01 '
#2120000000
0"
0%
#2130000000
1"
b10 #
1%
b10 &
b10 '
#2140000000
0"
0%
#2150000000
1"
b11 #
1%
b11 &
b11 '
#2160000000
0"
0%
#2170000000
1"
b00 #
1%
b00 &
b00 '
#2180000000
0"
0%
#2190000000
1"
b01 #
1%
b01 &
b01 '
#2200000000
0"
0%
#2210000000
1"
b10 #
1%
b10 &
b10 '
#2220000000
0"
0%
#2230000000
1"
b11 #
1%
b11 &
b11 '
#2240000000
0"
0%
#2250000000
1"
b00 #
1%
b00 &
b00 '
#2260000000
0"
0%
#2270000000
1"
b01 #
1%
b01 &
b01 '
#2280000000
0"
0%
#2290000000
1"
b10 #
1%
b10 &
b10 '
#2300000000
0"
0%
#2310000000
1"
b11 #
1%
b11 &
b11 '
#2320000000
0"
0%
#2330000000
1"
b00 #
1%
b00 &
b00 '
#2340000000
0"
0%
#2350000000
1"
b01 #
1%
b01 &
b01 '
#2360000000
0"
0%
#2370000000
1"
b10 #
1%
b10 &
b10 '
#2380000000
0"
0%
#2390000000
1"
b11 #
1%
b11 &
b11 '
#2400000000
0"
0%
#2410000000
1"
b00 #
1%
b00 &
b00 '
#2420000000
0"
0%
#2430000000
1"
b01 #
1%
b01 &
b01 '
#2440000000
0"
0%
#2450000000
1"
b10 #
1%
b10 &
b10 '
#2460000000
0"
0%
#2470000000
1"
b11 #
1%
b11 &
b11 '
#2480000000
0"
0%
#2490000000
1"
b00 #
1%
b00 &
b00 '
#2500000000
0"
0%
#2510000000
1"
b01 #
1%
b01 &
b01 '
#2520000000
0"
0%
#2530000000
1"
b10 #
1%
b10 &
b10 '
#2540000000
0"
0%
#2550000000
1"
b11 #
1%
b11 &
b11 '
#2560000000
0"
0%
#2570000000
1"
b00 #
1%
b00 &
b00 '
#2580000000
0"
0%
#2590000000
1"
b01 #
1%
b01 &
b01 '
#2600000000
0"
0%
#2610000000
1"
b10 #
1%
b10 &
b10 '
#2620000000
0"
0%
#2630000000
1"
b11 #
1%
b11 &
b11 '
#2640000000
0"
0%
#2650000000
1"
b00 #
1%
b00 &
b00 '
#2660000000
0"
0%
#2670000000
1"
b01 #
1%
b01 &
b01 '
#2680000000
0"
0%
#2690000000
1"
b10 #
1%
b10 &
b10 '
#2700000000
0"
0%
#2710000000
1"
b11 #
1%
b11 &
b11 '
#2720000000
0"
0%
#2730000000
1"
b00 #
1%
b00 &
b00 '
#2740000000
0"
0%
#2750000000
1"
b01 #
1%
b01 &
b01 '
#2760000000
0"
0%
#2770000000
1"
b10 #
1%
b10 &
b10 '
#2780000000
0"
0%
#2790000000
1"
b11 #
1%
b11 &
b11 '
#2800000000
0"
0%
#2810000000
1"
b00 #
1%
b00 &
b00 '
#2820000000
0"
0%
#2830000000
1"
b01 #
1%
b01 &
b01 '
#2840000000
0"
0%
#2850000000
1"
b10 #
1%
b10 &
b10 '
#2860000000
0"
0%
#2870000000
1"
b11 #
1%
b11 &
b11 '
#2880000000
0"
0%
#2890000000
1"
b00 #
1%
b00 &
b00 '
#2900000000
0"
0%
#2910000000
1"
b01 #
1%
b01 &
b01 '
#2920000000
0"
0%
#2930000000
1"
b10 #
1%
b10 &
b10 '
#2940000000
0"
0%
#2950000000
1"
b11 #
1%
b11 &
b11 '
#2960000000
0"
0%
#2970000000
1"
b00 #
1%
b00 &
b00 '
#2980000000
0"
0%
#2990000000
1"
b01 #
1%
b01 &
b01 '
#3000000000
0"
0%
#3010000000
1"
b10 #
1%
b10 &
b10 '
#3020000000
0"
0%
#3030000000
1"
b11 #
1%
b11 &
b11 '
#3040000000
0"
0%
#3050000000
1"
b00 #
1%
b00 &
b00 '
#3060000000
0"
0%
#3070000000
1"
b01 #
1%
b01 &
b01 '
#3080000000
0"
0%
#3090000000
1"
b10 #
1%
b10 &
b10 '
#3100000000
0"
0%
#3110000000
1"
b11 #
1%
b11 &
b11 '
#3120000000
0"
0%
#3130000000
1"
b00 #
1%
b00 &
b00 '
#3140000000
0"
0%
#3150000000
1"
b01 #
1%
b01 &
b01 '
#3160000000
0"
0%
#3170000000
1"
b10 #
1%
b10 &
b10 '
#3180000000
0"
0%
#3190000000
1"
b11 #
1%
b11 &
b11 '
#3200000000
0"
0%
#3210000000
1"
b00 #
1%
b00 &
b00 '
#3220000000
0"
0%
#3230000000
1"
b01 #
1%
b01 &
b01 '
#3240000000
0"
0%
#3250000000
1"
b10 #
1%
b10 &
b10 '
#3260000000
0"
0%
#3270000000
1"
b11 #
1%
b11 &
b11 '
#3280000000
0"
0%
#3290000000
1"
b00 #
1%
b00 &
b00 '
#3300000000
0"
0%
#3310000000
1"
b01 #
1%
b01 &
b01 '
#3320000000
0"
0%
#3330000000
1"
b10 #
1%
b10 &
b10 '
#3340000000
0"
0%
#3350000000
1"
b11 #
1%
b11 &
b11 '
#3360000000
0"
0%
#3370000000
1"
b00 #
1%
b00 &
b00 '
#3380000000
0"
0%
#3390000000
1"
b01 #
1%
b01 &
b01 '
#3400000000
0"
0%
#3410000000
1"
b10 #
1%
b10 &
b10 '
#3420000000
0"
0%
#3430000000
1"
b11 #
1%
b11 &
b11 '
#3440000000
0"
0%
#3450000000
1"
b00 #
1%
b00 &
b00 '
#3460000000
0"
0%
#3470000000
1"
b01 #
1%
b01 &
b01 '
#3480000000
0"
0%
#3490000000
1"
b10 #
1%
b10 &
b10 '
#3500000000
0"
0%
#3510000000
1"
b11 #
1%
b11 &
b11 '
#3520000000
0"
0%
#3530000000
1"
b00 #
1%
b00 &
b00 '
#3540000000
0"
0%
#3550000000
1"
b01 #
1%
b01 &
b01 '
#3560000000
0"
0%
#3570000000
1"
b10 #
1%
b10 &
b10 '
#3580000000
0"
0%
#3590000000
1"
b11 #
1%
b11 &
b11 '
#3600000000
0"
0%
#3610000000
1"
b00 #
1%
b00 &
b00 '
#3620000000
0"
0%
#3630000000
1"
b01 #
1%
b01 &
b01 '
#3640000000
0"
0%
#3650000000
1"
b10 #
1%
b10 &
b10 '
#3660000000
0"
0%
#3670000000
1"
b11 #
1%
b11 &
b11 '
#3680000000
0"
0%
#3690000000
1"
b00 #
1%
b00 &
b00 '
#3700000000
0"
0%
#3710000000
1"
b01 #
1%
b01 &
b01 '
#3720000000
0"
0%
#3730000000
1"
b10 #
1%
b10 &
b10 '
#3740000000
0"
0%
#3750000000
1"
b11 #
1%
b11 &
b11 '
#3760000000
0"
0%
#3770000000
1"
b00 #
1%
b00 &
b00 '
#3780000000
0"
0%
#3790000000
1"
b01 #
1%
b01 &
b01 '
#3800000000
0"
0%
#3810000000
1"
b10 #
1%
b10 &
b10 '
#3820000000
0"
0%
#3830000000
1"
b11 #
1%
b11 &
b11 '
#3840000000
0"
0%
#3850000000
1"
b00 #
1%
b00 &
b00 '
#3860000000
0"
0%
#3870000000
1"
b01 #
1%
b01 &
b01 '
#3880000000
0"
0%
#3890000000
1"
b10 #
1%
b10 &
b10 '
#3900000000
0"
0%
#3910000000
1"
b11 #
1%
b11 &
b11 '
#3920000000
0"
0%
#3930000000
1"
b00 #
1%
b00 &
b00 '
#3940000000
0"
0%
#3950000000
1"
b01 #
1%
b01 &
b01 '
#3960000000
0"
0%
#3970000000
1"
b10 #
1%
b10 &
b10 '
#3980000000
0"
0%
#3990000000
1"
b11 #
1%
b11 &
b11 '
#4000000000
0"
0%
#4010000000
1"
b00 #
1%
b00 &
b00 '
#4020000000
0"
0%
#4030000000
1"
b01 #
1%
b01 &
b01 '
#4040000000
0"
0%
#4050000000
1"
b10 #
1%
b10 &
b10 '
#4060000000
0"
0%
#4070000000
1"
b11 #
1%
b11 &
b11 '
#4080000000
0"
0%
#4090000000
1"
b00 #
1%
b00 &
b00 '
#4100000000
0"
0%
#4110000000
1"
b01 #
1%
b01 &
b01 '
#4120000000
0"
0%
#4130000000
1"
b10 #
1%
b10 &
b10 '
#4140000000
0"
0%
#4150000000
1"
b11 #
1%
b11 &
b11 '
#4160000000
0"
0%
#4170000000
1"
b00 #
1%
b00 &
b00 '
#4180000000
0"
0%
#4190000000
1"
b01 #
1%
b01 &
b01 '
#4200000000
0"
0%
#4210000000
1"
b10 #
1%
b10 &
b10 '
#4220000000
0"
0%
#4230000000
1"
b11 #
1%
b11 &
b11 '
#4240000000
0"
0%
#4250000000
1"
b00 #
1%
b00 &
b00 '
#4260000000
0"
0%
#4270000000
1"
b01 #
1%
b01 &
b01 '
#4280000000
0"
0%
#4290000000
1"
b10 #
1%
b10 &
b10 '
#4300000000
0"
0%
#4310000000
1"
b11 #
1%
b11 &
b11 '
#4320000000
0"
0%
#4330000000
1"
b00 #
1%
b00 &
b00 '
#4340000000
0"
0%
#4350000000
1"
b01 #
1%
b01 &
b01 '
#4360000000
0"
0%
#4370000000
1"
b10 #
1%
b10 &
b10 '
#4380000000
0"
0%
#4390000000
1"
b11 #
1%
b11 &
b11 '
#4400000000
0"
0%
#4410000000
1"
b00 #
1%
b00 &
b00 '
#4420000000
0"
0%
#4430000000
1"
b01 #
1%
b01 &
b01 '
#4440000000
0"
0%
#4450000000
1"
b10 #
1%
b10 &
b10 '
#4460000000
0"
0%
#4470000000
1"
b11 #
1%
b11 &
b11 '
#4480000000
0"
0%
#4490000000
1"
b00 #
1%
b00 &
b00 '
#4500000000
0"
0%
#4510000000
1"
b01 #
1%
b01 &
b01 '
#4520000000
0"
0%
#4530000000
1"
b10 #
1%
b10 &
b10 '
#4540000000
0"
0%
#4550000000
1"
b11 #
1%
b11 &
b11 '
#4560000000
0"
0%
#4570000000
1"
b00 #
1%
b00 &
b00 '
#4580000000
0"
0%
#4590000000
1"
b01 #
1%
b01 &
b01 '
#4600000000
0"
0%
#4610000000
1"
b10 #
1%
b10 &
b10 '
#4620000000
0"
0%
#4630000000
1"
b11 #
1%
b11 &
b11 '
#4640000000
0"
0%
#4650000000
1"
b00 #
1%
b00 &
b00 '
#4660000000
0"
0%
#4670000000
1"
b01 #
1%
b01 &
b01 '
#4680000000
0"
0%
#4690000000
1"
b10 #
1%
b10 &
b10 '
#4700000000
0"
0%
#4710000000
1"
b11 #
1%
b11 &
b11 '
#4720000000
0"
0%
#4730000000
1"
b00 #
1%
b00 &
b00 '
#4740000000
0"
0%
#4750000000
1"
b01 #
1%
b01 &
b01 '
#4760000000
0"
0%
#4770000000
1"
b10 #
1%
b10 &
b10 '
#4780000000
0"
0%
#4790000000
1"
b11 #
1%
b11 &
b11 '
#4800000000
0"
0%
#4810000000
1"
b00 #
1%
b00 &
b00 '
#4820000000
0"
0%
#4830000000
1"
b01 #
1%
b01 &
b01 '
#4840000000
0"
0%
#4850000000
1"
b10 #
1%
b10 &
b10 '
#4860000000
0"
0%
#4870000000
1"
b11 #
1%
b11 &
b11 '
#4880000000
0"
0%
#4890000000
1"
b00 #
1%
b00 &
b00 '
#4900000000
0"
0%
#4910000000
1"
b01 #
1%
b01 &
b01 '
#4920000000
0"
0%
#4930000000
1"
b10 #
1%
b10 &
b10 '
#4940000000
0"
0%
#4950000000
1"
b11 #
1%
b11 &
b11 '
#4960000000
0"
0%
#4970000000
1"
b00 #
1%
b00 &
b00 '
#4980000000
0"
0%
#4990000000
1"
b01 #
1%
b01 &
b01 '
#5000000000
0"
0%
#5010000000
1"
b10 #
1%
b10 &
b10 '
#5020000000
0"
0%
#5030000000
1"
b11 #
1%
b11 &
b11 '
#5040000000
0"
0%
#5050000000
1"
b00 #
1%
b00 &
b00 '
#5060000000
0"
0%
#5070000000
1"
b01 #
1%
b01 &
b01 '
#5080000000
0"
0%
#5090000000
1"
b10 #
1%
b10 &
b10 '
#5100000000
0"
0%
#5110000000
1"
b11 #
1%
b11 &
b11 '
#5120000000
0"
0%
#5130000000
1"
b00 #
1%
b00 &
b00 '
#5140000000
0"
0%
#5150000000
1"
b01 #
1%
b01 &
b01 '
#5160000000
0"
0%
#5170000000
1"
b10 #
1%
b10 &
b10 '
#5180000000
0"
0%
#5190000000
1"
b11 #
1%
b11 &
b11 '
#5200000000
0"
0%
#5210000000
1"
b00 #
1%
b00 &
b00 '
#5220000000
0"
0%
#5230000000
1"
b01 #
1%
b01 &
b01 '
#5240000000
0"
0%
#5250000000
1"
b10 #
1%
b10 &
b10 '
#5260000000
0"
0%
#5270000000
1"
b11 #
1%
b11 &
b11 '
#5280000000
0"
0%
#5290000000
1"
b00 #
1%
b00 &
b00 '
#5300000000
0"
0%
#5310000000
1"
b01 #
1%
b01 &
b01 '
#5320000000
0"
0%
#5330000000
1"
b10 #
1%
b10 &
b10 '
#5340000000
0"
0%
#5350000000
1"
b11 #
1%
b11 &
b11 '
#5360000000
0"
0%
#5370000000
1"
b00 #
1%
b00 &
b00 '
#5380000000
0"
0%
#5390000000
1"
b01 #
1%
b01 &
b01 '
#5400000000
0"
0%
#5410000000
1"
b10 #
1%
b10 &
b10 '
#5420000000
0"
0%
#5430000000
1"
b11 #
1%
b11 &
b11 '
#5440000000
0"
0%
#5450000000
1"
b00 #
1%
b00 &
b00 '
#5460000000
0"
0%
#5470000000
1"
b01 #
1%
b01 &
b01 '
#5480000000
0"
0%
#5490000000
1"
b10 #
1%
b10 &
b10 '
#5500000000
0"
0%
#5510000000
1"
b11 #
1%
b11 &
b11 '
#5520000000
0"
0%
#5530000000
1"
b00 #
1%
b00 &
b00 '
#5540000000
0"
0%
#5550000000
1"
b01 #
1%
b01 &
b01 '
#5560000000
0"
0%
#5570000000
1"
b10 #
1%
b10 &
b10 '
#5580000000
0"
0%
#5590000000
1"
b11 #
1%
b11 &
b11 '
#5600000000
0"
0%
#5610000000
1"
b00 #
1%
b00 &
b00 '
#5620000000
0"
0%
#5630000000
1"
b01 #
1%
b01 &
b01 '
#5640000000
0"
0%
#5650000000
1"
b10 #
1%
b10 &
b10 '
#5660000000
0"
0%
#5670000000
1"
b11 #
1%
b11 &
b11 '
#5680000000
0"
0%
#5690000000
1"
b00 #
1%
b00 &
b00 '
#5700000000
0"
0%
#5710000000
1"
b01 #
1%
b01 &
b01 '
#5720000000
0"
0%
#5730000000
1"
b10 #
1%
b10 &
b10 '
#5740000000
0"
0%
#5750000000
1"
b11 #
1%
b11 &
b11 '
#5760000000
0"
0%
#5770000000
1"
b00 #
1%
b00 &
b00 '
#5780000000
0"
0%
#5790000000
1"
b01 #
1%
b01 &
b01 '
#5800000000
0"
0%
#5810000000
1"
b10 #
1%
b10 &
b10 '
#5820000000
0"
0%
#5830000000
1"
b11 #
1%
b11 &
b11 '
#5840000000
0"
0%
#5850000000
1"
b00 #
1%
b00 &
b00 '
#5860000000
0"
0%
#5870000000
1"
b01 #
1%
b01 &
b01 '
#5880000000
0"
0%
#5890000000
1"
b10 #
1%
b10 &
b10 '
#5900000000
0"
0%
#5910000000
1"
b11 #
1%
b11 &
b11 '
#5920000000
0"
0%
#5930000000
1"
b00 #
1%
b00 &
b00 '
#5940000000
0"
0%
#5950000000
1"
b01 #
1%
b01 &
b01 '
#5960000000
0"
0%
#5970000000
1"
b10 #
1%
b10 &
b10 '
#5980000000
0"
0%
#5990000000
1"
b11 #
1%
b11 &
b11 '
#6000000000
0"
0%
#6010000000
1"
b00 #
1%
b00 &
b00 '
#6020000000
0"
0%
#6030000000
1"
b01 #
1%
b01 &
b01 '
#6040000000
0"
0%
#6050000000
1"
b10 #
1%
b10 &
b10 '
#6060000000
0"
0%
#6070000000
1"
b11 #
1%
b11 &
b11 '
#6080000000
0"
0%
#6090000000
1"
b00 #
1%
b00 &
b00 '
#6100000000
0"
0%
#6110000000
1"
b01 #
1%
b01 &
b01 '
#6120000000
0"
0%
#6130000000
1"
b10 #
1%
b10 &
b10 '
#6140000000
0"
0%
#6150000000
1"
b11 #
1%
b11 &
b11 '
#6160000000
0"
0%
#6170000000
1"
b00 #
1%
b00 &
b00 '
#6180000000
0"
0%
#6190000000
1"
b01 #
1%
b01 &
b01 '
#6200000000
0"
0%
#6210000000
1"
b10 #
1%
b10 &
b10 '
#6220000000
0"
0%
#6230000000
1"
b11 #
1%
b11 &
b11 '
#6240000000
0"
0%
#6250000000
1"
b00 #
1%
b00 &
b00 '
#6260000000
0"
0%
#6270000000
1"
b01 #
1%
b01 &
b01 '
#6280000000
0"
0%
#6290000000
1"
b10 #
1%
b10 &
b10 '
#6300000000
0"
0%
#6310000000
1"
b11 #
1%
b11 &
b11 '
#6320000000
0"
0%
#6330000000
1"
b00 #
1%
b00 &
b00 '
#6340000000
0"
0%
#6350000000
1"
b01 #
1%
b01 &
b01 '
#6360000000
0"
0%
#6370000000
1"
b10 #
1%
b10 &
b10 '
#6380000000
0"
0%
#6390000000
1"
b11 #
1%
b11 &
b11 '
#6400000000
0"
0%
#6410000000
1"
b00 #
1%
b00 &
b00 '
#6420000000
0"
0%
#6430000000
1"
b01 #
1%
b01 &
b01 '
#6440000000
0"
0%
#6450000000
1"
b10 #
1%
b10 &
b10 '
#6460000000
0"
0%
#6470000000
1"
b11 #
1%
b11 &
b11 '
#6480000000
0"
0%
#6490000000
1"
b00 #
1%
b00 &
b00 '
#6500000000
0"
0%
#6510000000
1"
b01 #
1%
b01 &
b01 '
#6520000000
0"
0%
#6530000000
1"
b10 #
1%
b10 &
b10 '
#6540000000
0"
0%
#6550000000
1"
b11 #
1%
b11 &
b11 '
#6560000000
0"
0%
#6570000000
1"
b00 #
1%
b00 &
b00 '
#6580000000
0"
0%
#6590000000
1"
b01 #
1%
b01 &
b01 '
#6600000000
0"
0%
#6610000000
1"
b10 #
1%
b10 &
b10 '
#6620000000
0"
0%
#6630000000
1"
b11 #
1%
b11 &
b11 '
#6640000000
0"
0%
#6650000000
1"
b00 #
1%
b00 &
b00 '
#6660000000
0"
0%
#6670000000
1"
b01 #
1%
b01 &
b01 '
#6680000000
0"
0%
#6690000000
1"
b10 #
1%
b10 &
b10 '
#6700000000
0"
0%
#6710000000
1"
b11 #
1%
b11 &
b11 '
#6720000000
0"
0%
#6730000000
1"
b00 #
1%
b00 &
b00 '
#6740000000
0"
0%
#6750000000
1"
b01 #
1%
b01 &
b01 '
#6760000000
0"
0%
#6770000000
1"
b10 #
1%
b10 &
b10 '
#6780000000
0"
0%
#6790000000
1"
b11 #
1%
b11 &
b11 '
#6800000000
0"
0%
#6810000000
1"
b00 #
1%
b00 &
b00 '
#6820000000
0"
0%
#6830000000
1"
b01 #
1%
b01 &
b01 '
#6840000000
0"
0%
#6850000000
1"
b10 #
1%
b10 &
b10 '
#6860000000
0"
0%
#6870000000
1"
b11 #
1%
b11 &
b11 '
#6880000000
0"
0%
#6890000000
1"
b00 #
1%
b00 &
b00 '
#6900000000
0"
0%
#6910000000
1"
b01 #
1%
b01 &
b01 '
#6920000000
0"
0%
#6930000000
1"
b10 #
1%
b10 &
b10 '
#6940000000
0"
0%
#6950000000
1"
b11 #
1%
b11 &
b11 '
#6960000000
0"
0%
#6970000000
1"
b00 #
1%
b00 &
b00 '
#6980000000
0"
0%
#6990000000
1"
b01 #
1%
b01 &
b01 '
#7000000000
0"
0%
#7010000000
1"
b10 #
1%
b10 &
b10 '
#7020000000
0"
0%
#7030000000
1"
b11 #
1%
b11 &
b11 '
#7040000000
0"
0%
#7050000000
1"
b00 #
1%
b00 &
b00 '
#7060000000
0"
0%
#7070000000
1"
b01 #
1%
b01 &
b01 '
